epubedit/__init__.py
epubedit/epubedit.py
epubedit-0.1.1.dist-info/LICENSE
epubedit-0.1.1.dist-info/METADATA
epubedit-0.1.1.dist-info/WHEEL
epubedit-0.1.1.dist-info/top_level.txt
epubedit-0.1.1.dist-info/RECORD
