Metadata-Version: 2.2
Name: epubedit
Version: 0.1.1
Summary: a python package to read ePub infos and edit it.
Author: Youyu
License: Copyright (c) 2024 The Python Packaging Authority
Project-URL: homepage, https://github.com/childeyouyu/epubedit
Project-URL: repository, https://github.com/childeyouyu/epubedit
Project-URL: issues, https://github.com/childeyouyu/epubedit/issues
Keywords: epub,ebook,metadata search,content.opf,ebook-reader,ebook-editor,epub-tools,digital-publishing,ebook-converter,ebook-management,ebook-library,metadata,metadata-editor,epub-metadata
Classifier: Programming Language :: Python :: 3
Classifier: License :: OSI Approved :: MIT License
Classifier: Operating System :: OS Independent
Classifier: Development Status :: 5 - Production/Stable
Requires-Python: >=3.12.0
License-File: LICENSE
